[
  {
    "state": "US",
    "count": 444,
    "path": "./bills_by_state/US.json"
  },
  {
    "state": "NY",
    "count": 310,
    "path": "./bills_by_state/NY.json"
  },
  {
    "state": "CA",
    "count": 195,
    "path": "./bills_by_state/CA.json"
  },
  {
    "state": "IL",
    "count": 181,
    "path": "./bills_by_state/IL.json"
  },
  {
    "state": "NJ",
    "count": 174,
    "path": "./bills_by_state/NJ.json"
  },
  {
    "state": "MA",
    "count": 169,
    "path": "./bills_by_state/MA.json"
  },
  {
    "state": "HI",
    "count": 129,
    "path": "./bills_by_state/HI.json"
  },
  {
    "state": "VA",
    "count": 124,
    "path": "./bills_by_state/VA.json"
  },
  {
    "state": "WA",
    "count": 104,
    "path": "./bills_by_state/WA.json"
  },
  {
    "state": "TN",
    "count": 101,
    "path": "./bills_by_state/TN.json"
  },
  {
    "state": "TX",
    "count": 86,
    "path": "./bills_by_state/TX.json"
  },
  {
    "state": "FL",
    "count": 82,
    "path": "./bills_by_state/FL.json"
  },
  {
    "state": "OK",
    "count": 78,
    "path": "./bills_by_state/OK.json"
  },
  {
    "state": "RI",
    "count": 78,
    "path": "./bills_by_state/RI.json"
  },
  {
    "state": "MD",
    "count": 76,
    "path": "./bills_by_state/MD.json"
  },
  {
    "state": "MN",
    "count": 70,
    "path": "./bills_by_state/MN.json"
  },
  {
    "state": "GA",
    "count": 67,
    "path": "./bills_by_state/GA.json"
  },
  {
    "state": "MS",
    "count": 59,
    "path": "./bills_by_state/MS.json"
  },
  {
    "state": "IA",
    "count": 56,
    "path": "./bills_by_state/IA.json"
  },
  {
    "state": "UT",
    "count": 53,
    "path": "./bills_by_state/UT.json"
  },
  {
    "state": "AL",
    "count": 50,
    "path": "./bills_by_state/AL.json"
  },
  {
    "state": "LA",
    "count": 47,
    "path": "./bills_by_state/LA.json"
  },
  {
    "state": "PA",
    "count": 45,
    "path": "./bills_by_state/PA.json"
  },
  {
    "state": "SC",
    "count": 45,
    "path": "./bills_by_state/SC.json"
  },
  {
    "state": "MO",
    "count": 44,
    "path": "./bills_by_state/MO.json"
  },
  {
    "state": "CO",
    "count": 38,
    "path": "./bills_by_state/CO.json"
  },
  {
    "state": "NC",
    "count": 38,
    "path": "./bills_by_state/NC.json"
  },
  {
    "state": "AZ",
    "count": 37,
    "path": "./bills_by_state/AZ.json"
  },
  {
    "state": "VT",
    "count": 37,
    "path": "./bills_by_state/VT.json"
  },
  {
    "state": "NM",
    "count": 35,
    "path": "./bills_by_state/NM.json"
  },
  {
    "state": "WI",
    "count": 35,
    "path": "./bills_by_state/WI.json"
  },
  {
    "state": "ID",
    "count": 33,
    "path": "./bills_by_state/ID.json"
  },
  {
    "state": "OH",
    "count": 32,
    "path": "./bills_by_state/OH.json"
  },
  {
    "state": "KY",
    "count": 30,
    "path": "./bills_by_state/KY.json"
  },
  {
    "state": "WV",
    "count": 29,
    "path": "./bills_by_state/WV.json"
  },
  {
    "state": "CT",
    "count": 27,
    "path": "./bills_by_state/CT.json"
  },
  {
    "state": "MT",
    "count": 26,
    "path": "./bills_by_state/MT.json"
  },
  {
    "state": "DC",
    "count": 21,
    "path": "./bills_by_state/DC.json"
  },
  {
    "state": "AK",
    "count": 18,
    "path": "./bills_by_state/AK.json"
  },
  {
    "state": "OR",
    "count": 18,
    "path": "./bills_by_state/OR.json"
  },
  {
    "state": "KS",
    "count": 17,
    "path": "./bills_by_state/KS.json"
  },
  {
    "state": "NH",
    "count": 15,
    "path": "./bills_by_state/NH.json"
  },
  {
    "state": "NV",
    "count": 15,
    "path": "./bills_by_state/NV.json"
  },
  {
    "state": "MI",
    "count": 14,
    "path": "./bills_by_state/MI.json"
  },
  {
    "state": "IN",
    "count": 11,
    "path": "./bills_by_state/IN.json"
  },
  {
    "state": "NE",
    "count": 11,
    "path": "./bills_by_state/NE.json"
  },
  {
    "state": "AR",
    "count": 10,
    "path": "./bills_by_state/AR.json"
  },
  {
    "state": "ME",
    "count": 10,
    "path": "./bills_by_state/ME.json"
  },
  {
    "state": "ND",
    "count": 9,
    "path": "./bills_by_state/ND.json"
  },
  {
    "state": "WY",
    "count": 8,
    "path": "./bills_by_state/WY.json"
  },
  {
    "state": "SD",
    "count": 6,
    "path": "./bills_by_state/SD.json"
  },
  {
    "state": "DE",
    "count": 5,
    "path": "./bills_by_state/DE.json"
  },
  {
    "state": "PR",
    "count": 1,
    "path": "./bills_by_state/PR.json"
  }
]