[
  {
    "state": "NY",
    "total": 17664,
    "core": 252,
    "adjacent_only": 17385,
    "in_ncsl": 384
  },
  {
    "state": "IL",
    "total": 17078,
    "core": 114,
    "adjacent_only": 16746,
    "in_ncsl": 225
  },
  {
    "state": "MN",
    "total": 9166,
    "core": 34,
    "adjacent_only": 9058,
    "in_ncsl": 74
  },
  {
    "state": "US",
    "total": 8646,
    "core": 419,
    "adjacent_only": 8227,
    "in_ncsl": 0
  },
  {
    "state": "MA",
    "total": 8603,
    "core": 158,
    "adjacent_only": 8432,
    "in_ncsl": 159
  },
  {
    "state": "MS",
    "total": 8286,
    "core": 62,
    "adjacent_only": 8176,
    "in_ncsl": 48
  },
  {
    "state": "NJ",
    "total": 8174,
    "core": 111,
    "adjacent_only": 8017,
    "in_ncsl": 190
  },
  {
    "state": "NC",
    "total": 6754,
    "core": 38,
    "adjacent_only": 6642,
    "in_ncsl": 74
  },
  {
    "state": "CA",
    "total": 6635,
    "core": 158,
    "adjacent_only": 6268,
    "in_ncsl": 222
  },
  {
    "state": "VA",
    "total": 5967,
    "core": 125,
    "adjacent_only": 5731,
    "in_ncsl": 111
  },
  {
    "state": "WA",
    "total": 5362,
    "core": 75,
    "adjacent_only": 5208,
    "in_ncsl": 81
  },
  {
    "state": "HI",
    "total": 4900,
    "core": 106,
    "adjacent_only": 4664,
    "in_ncsl": 183
  },
  {
    "state": "OK",
    "total": 4675,
    "core": 74,
    "adjacent_only": 4538,
    "in_ncsl": 68
  },
  {
    "state": "TX",
    "total": 4520,
    "core": 86,
    "adjacent_only": 4268,
    "in_ncsl": 181
  },
  {
    "state": "RI",
    "total": 4399,
    "core": 60,
    "adjacent_only": 4264,
    "in_ncsl": 75
  },
  {
    "state": "AZ",
    "total": 3696,
    "core": 54,
    "adjacent_only": 3592,
    "in_ncsl": 50
  },
  {
    "state": "DC",
    "total": 3492,
    "core": 20,
    "adjacent_only": 3464,
    "in_ncsl": 8
  },
  {
    "state": "WV",
    "total": 3316,
    "core": 36,
    "adjacent_only": 3237,
    "in_ncsl": 47
  },
  {
    "state": "MO",
    "total": 3091,
    "core": 35,
    "adjacent_only": 2996,
    "in_ncsl": 60
  },
  {
    "state": "FL",
    "total": 2902,
    "core": 52,
    "adjacent_only": 2747,
    "in_ncsl": 111
  },
  {
    "state": "UT",
    "total": 2870,
    "core": 37,
    "adjacent_only": 2786,
    "in_ncsl": 47
  },
  {
    "state": "KY",
    "total": 2772,
    "core": 24,
    "adjacent_only": 2712,
    "in_ncsl": 39
  },
  {
    "state": "GA",
    "total": 2582,
    "core": 44,
    "adjacent_only": 2480,
    "in_ncsl": 79
  },
  {
    "state": "MI",
    "total": 2549,
    "core": 10,
    "adjacent_only": 2508,
    "in_ncsl": 31
  },
  {
    "state": "TN",
    "total": 2469,
    "core": 59,
    "adjacent_only": 2333,
    "in_ncsl": 77
  },
  {
    "state": "IA",
    "total": 2400,
    "core": 20,
    "adjacent_only": 2325,
    "in_ncsl": 62
  },
  {
    "state": "MD",
    "total": 2163,
    "core": 61,
    "adjacent_only": 1925,
    "in_ncsl": 177
  },
  {
    "state": "SC",
    "total": 1991,
    "core": 24,
    "adjacent_only": 1955,
    "in_ncsl": 45
  },
  {
    "state": "IN",
    "total": 1800,
    "core": 11,
    "adjacent_only": 1756,
    "in_ncsl": 33
  },
  {
    "state": "AR",
    "total": 1779,
    "core": 10,
    "adjacent_only": 1738,
    "in_ncsl": 31
  },
  {
    "state": "NM",
    "total": 1636,
    "core": 28,
    "adjacent_only": 1581,
    "in_ncsl": 38
  },
  {
    "state": "CO",
    "total": 1628,
    "core": 27,
    "adjacent_only": 1558,
    "in_ncsl": 43
  },
  {
    "state": "AL",
    "total": 1551,
    "core": 32,
    "adjacent_only": 1474,
    "in_ncsl": 47
  },
  {
    "state": "MT",
    "total": 1529,
    "core": 26,
    "adjacent_only": 1457,
    "in_ncsl": 46
  },
  {
    "state": "PA",
    "total": 1472,
    "core": 38,
    "adjacent_only": 1368,
    "in_ncsl": 73
  },
  {
    "state": "LA",
    "total": 1311,
    "core": 20,
    "adjacent_only": 1271,
    "in_ncsl": 26
  },
  {
    "state": "ID",
    "total": 1309,
    "core": 19,
    "adjacent_only": 1288,
    "in_ncsl": 19
  },
  {
    "state": "OR",
    "total": 1294,
    "core": 18,
    "adjacent_only": 1234,
    "in_ncsl": 42
  },
  {
    "state": "OH",
    "total": 1177,
    "core": 19,
    "adjacent_only": 1134,
    "in_ncsl": 27
  },
  {
    "state": "NE",
    "total": 1080,
    "core": 10,
    "adjacent_only": 1050,
    "in_ncsl": 25
  },
  {
    "state": "NV",
    "total": 1049,
    "core": 15,
    "adjacent_only": 990,
    "in_ncsl": 44
  },
  {
    "state": "KS",
    "total": 965,
    "core": 6,
    "adjacent_only": 939,
    "in_ncsl": 20
  },
  {
    "state": "VT",
    "total": 962,
    "core": 28,
    "adjacent_only": 927,
    "in_ncsl": 34
  },
  {
    "state": "WI",
    "total": 953,
    "core": 18,
    "adjacent_only": 906,
    "in_ncsl": 29
  },
  {
    "state": "DE",
    "total": 691,
    "core": 7,
    "adjacent_only": 677,
    "in_ncsl": 12
  },
  {
    "state": "CT",
    "total": 689,
    "core": 27,
    "adjacent_only": 602,
    "in_ncsl": 60
  },
  {
    "state": "AK",
    "total": 631,
    "core": 13,
    "adjacent_only": 601,
    "in_ncsl": 18
  },
  {
    "state": "ME",
    "total": 606,
    "core": 8,
    "adjacent_only": 551,
    "in_ncsl": 47
  },
  {
    "state": "NH",
    "total": 604,
    "core": 14,
    "adjacent_only": 574,
    "in_ncsl": 16
  },
  {
    "state": "ND",
    "total": 543,
    "core": 9,
    "adjacent_only": 506,
    "in_ncsl": 28
  },
  {
    "state": "WY",
    "total": 456,
    "core": 6,
    "adjacent_only": 438,
    "in_ncsl": 12
  },
  {
    "state": "SD",
    "total": 201,
    "core": 5,
    "adjacent_only": 189,
    "in_ncsl": 7
  },
  {
    "state": "PR",
    "total": 125,
    "core": 1,
    "adjacent_only": 96,
    "in_ncsl": 28
  },
  {
    "state": "GU",
    "total": 5,
    "core": 0,
    "adjacent_only": 0,
    "in_ncsl": 5
  },
  {
    "state": "VI",
    "total": 1,
    "core": 0,
    "adjacent_only": 0,
    "in_ncsl": 1
  }
]