[
  {
    "bill_id": "ocd-bill/0bc27871-ec98-4b9b-919a-7f4f21fbd092",
    "state": "NC",
    "session": "2025",
    "identifier": "HB 1004",
    "title": "UNC Artificial Intelligence and Technology Hubs.",
    "updated": "",
    "core_ai_hits": 2,
    "adjacent_ai_hits": 3,
    "matched_concepts": [
      "artificial_intelligence",
      "machine_learning",
      "adjacent_tech"
    ],
    "matched_tiers": [
      "adjacent_ai",
      "core_ai"
    ],
    "match_fields": [
      "title",
      "raw_text"
    ],
    "in_ncsl": true,
    "source_bucket": "regex_flagged",
    "primary_url": "https://www.ncleg.gov/Sessions/2025/Bills/House/PDF/H1004v0.pdf",
    "latest_action_date": "2025-04-14",
    "latest_action_description": "Ref to the Com on Appropriations, if favorable, Rules, Calendar, and Operations of the House",
    "ncsl_status": ""
  },
  {
    "bill_id": "ocd-bill/3dcb52aa-93b3-473d-8d0e-abd27efd6e8f",
    "state": "NC",
    "session": "2023",
    "identifier": "HB 1004",
    "title": "Artificial Intelligence Study Committee/Funds.",
    "updated": "",
    "core_ai_hits": 1,
    "adjacent_ai_hits": 1,
    "matched_concepts": [
      "artificial_intelligence"
    ],
    "matched_tiers": [
      "adjacent_ai",
      "core_ai"
    ],
    "match_fields": [
      "title",
      "raw_text"
    ],
    "in_ncsl": true,
    "source_bucket": "regex_flagged",
    "primary_url": "https://www.ncleg.gov/Sessions/2023/Bills/House/PDF/H1004v0.pdf",
    "latest_action_date": "2024-05-06",
    "latest_action_description": "Ref to the Com on Appropriations, if favorable, Rules, Calendar, and Operations of the House",
    "ncsl_status": ""
  },
  {
    "bill_id": "ocd-bill/95abc28e-6a3b-4d04-88d6-7d2416d9fc37",
    "state": "NC",
    "session": "2021",
    "identifier": "HB 103",
    "title": "2022 Appropriations Act.",
    "updated": "",
    "core_ai_hits": 1,
    "adjacent_ai_hits": 0,
    "matched_concepts": [
      "artificial_intelligence"
    ],
    "matched_tiers": [
      "core_ai"
    ],
    "match_fields": [
      "raw_text"
    ],
    "in_ncsl": false,
    "source_bucket": "regex_flagged",
    "primary_url": "https://www.ncleg.gov/Sessions/2021/Bills/House/PDF/H103v5.pdf",
    "latest_action_date": "2022-07-11",
    "latest_action_description": "Ch. SL 2022-74",
    "ncsl_status": ""
  },
  {
    "bill_id": "ocd-bill/32144278-5d3e-48ed-a92a-a42587547979",
    "state": "NC",
    "session": "2023",
    "identifier": "HB 1036",
    "title": "Artificial Intelligence Task Force/Funds.",
    "updated": "",
    "core_ai_hits": 5,
    "adjacent_ai_hits": 3,
    "matched_concepts": [
      "adjacent_tech",
      "ai_system_composite",
      "machine_learning",
      "artificial_intelligence",
      "automated_decision_system",
      "ai_system"
    ],
    "matched_tiers": [
      "adjacent_ai",
      "core_ai"
    ],
    "match_fields": [
      "title",
      "raw_text"
    ],
    "in_ncsl": true,
    "source_bucket": "regex_flagged",
    "primary_url": "https://www.ncleg.gov/Sessions/2023/Bills/House/PDF/H1036v0.pdf",
    "latest_action_date": "2024-05-07",
    "latest_action_description": "Ref to the Com on Appropriations, if favorable, Rules, Calendar, and Operations of the House",
    "ncsl_status": ""
  },
  {
    "bill_id": "ocd-bill/07a5a76b-205a-457c-9708-f6944feef7df",
    "state": "NC",
    "session": "2023",
    "identifier": "HB 1072",
    "title": "Require Disclaimer/Use of Artificial Intelligence in Political Advertisements.",
    "updated": "",
    "core_ai_hits": 1,
    "adjacent_ai_hits": 0,
    "matched_concepts": [
      "artificial_intelligence"
    ],
    "matched_tiers": [
      "core_ai"
    ],
    "match_fields": [
      "title"
    ],
    "in_ncsl": true,
    "source_bucket": "regex_flagged",
    "primary_url": null,
    "latest_action_date": "2024-06-27",
    "latest_action_description": "Ref To Com On Rules and Operations of the Senate",
    "ncsl_status": ""
  },
  {
    "bill_id": "ocd-bill/0050edca-cd55-4d7a-9c9f-cafbd15fae1b",
    "state": "NC",
    "session": "2025",
    "identifier": "HB 125",
    "title": "Continuing Budget Operations.",
    "updated": "",
    "core_ai_hits": 1,
    "adjacent_ai_hits": 0,
    "matched_concepts": [
      "artificial_intelligence"
    ],
    "matched_tiers": [
      "core_ai"
    ],
    "match_fields": [
      "raw_text"
    ],
    "in_ncsl": true,
    "source_bucket": "regex_flagged",
    "primary_url": "https://www.ncleg.gov/Sessions/2025/Bills/House/PDF/H125v5.pdf",
    "latest_action_date": "2025-08-06",
    "latest_action_description": "Ch. SL 2025-89",
    "ncsl_status": ""
  },
  {
    "bill_id": "ocd-bill/7ce1c497-47af-4fed-8a70-e5b57b803b20",
    "state": "NC",
    "session": "2021",
    "identifier": "HB 245",
    "title": "Efficient Government Buildings and Savings Act.",
    "updated": "",
    "core_ai_hits": 1,
    "adjacent_ai_hits": 1,
    "matched_concepts": [
      "machine_learning"
    ],
    "matched_tiers": [
      "adjacent_ai",
      "core_ai"
    ],
    "match_fields": [
      "raw_text"
    ],
    "in_ncsl": true,
    "source_bucket": "regex_flagged",
    "primary_url": "https://www.ncleg.gov/Sessions/2021/Bills/House/PDF/H245v0.pdf",
    "latest_action_date": "2021-04-22",
    "latest_action_description": "Ref To Com On Rules and Operations of the Senate",
    "ncsl_status": ""
  },
  {
    "bill_id": "ocd-bill/5ea4117b-5e92-4168-a3d8-d29ba7806018",
    "state": "NC",
    "session": "2019",
    "identifier": "HB 330",
    "title": "Efficient Government Buildings & Savings Act.",
    "updated": "",
    "core_ai_hits": 1,
    "adjacent_ai_hits": 1,
    "matched_concepts": [
      "machine_learning"
    ],
    "matched_tiers": [
      "core_ai",
      "adjacent_ai"
    ],
    "match_fields": [
      "raw_text"
    ],
    "in_ncsl": true,
    "source_bucket": "regex_flagged",
    "primary_url": "http://www.ncleg.net/Sessions/2019/Bills/House/PDF/H330v0.pdf",
    "latest_action_date": "2019-04-04",
    "latest_action_description": "Ref To Com On Rules and Operations of the Senate",
    "ncsl_status": ""
  },
  {
    "bill_id": "ocd-bill/9a6c2d10-0055-45f9-b796-c5492d768469",
    "state": "NC",
    "session": "2025",
    "identifier": "HB 375",
    "title": "Artificial Intelligence/Ban Deceptive Ads.",
    "updated": "",
    "core_ai_hits": 5,
    "adjacent_ai_hits": 2,
    "matched_concepts": [
      "machine_learning",
      "artificial_intelligence",
      "synthetic_media",
      "deepfake_media",
      "generative_ai_variant"
    ],
    "matched_tiers": [
      "core_ai",
      "adjacent_ai"
    ],
    "match_fields": [
      "title",
      "raw_text"
    ],
    "in_ncsl": true,
    "source_bucket": "regex_flagged",
    "primary_url": "https://www.ncleg.gov/Sessions/2025/Bills/House/PDF/H375v0.pdf",
    "latest_action_date": "2025-03-13",
    "latest_action_description": "Ref to the Com on Commerce and Economic Development, if favorable, Election Law, if favorable, Judiciary 2, if favorable, Rules, Calendar, and Operations of the House",
    "ncsl_status": ""
  },
  {
    "bill_id": "ocd-bill/4d61af7b-36e0-425c-beb0-1ef049fb0b18",
    "state": "NC",
    "session": "2025",
    "identifier": "HB 507",
    "title": "The Children First Act.",
    "updated": "",
    "core_ai_hits": 1,
    "adjacent_ai_hits": 0,
    "matched_concepts": [
      "artificial_intelligence"
    ],
    "matched_tiers": [
      "core_ai"
    ],
    "match_fields": [
      "raw_text"
    ],
    "in_ncsl": false,
    "source_bucket": "regex_flagged",
    "primary_url": "https://www.ncleg.gov/Sessions/2025/Bills/House/PDF/H507v0.pdf",
    "latest_action_date": "2025-03-26",
    "latest_action_description": "Ref To Com On Rules, Calendar, and Operations of the House",
    "ncsl_status": ""
  },
  {
    "bill_id": "ocd-bill/bd67534d-74ad-4f26-9ef4-37c70ccdf216",
    "state": "NC",
    "session": "2025",
    "identifier": "HB 638",
    "title": "Equitable Escalation of Electricity Demand Act.",
    "updated": "",
    "core_ai_hits": 1,
    "adjacent_ai_hits": 1,
    "matched_concepts": [
      "artificial_intelligence"
    ],
    "matched_tiers": [
      "adjacent_ai",
      "core_ai"
    ],
    "match_fields": [
      "raw_text"
    ],
    "in_ncsl": true,
    "source_bucket": "regex_flagged",
    "primary_url": "https://www.ncleg.gov/Sessions/2025/Bills/House/PDF/H638v0.pdf",
    "latest_action_date": "2025-04-02",
    "latest_action_description": "Ref to the Com on Energy and Public Utilities, if favorable, Finance, if favorable, Rules, Calendar, and Operations of the House",
    "ncsl_status": ""
  },
  {
    "bill_id": "ocd-bill/eb2f5444-e2a2-4beb-a571-efc8a030ad83",
    "state": "NC",
    "session": "2025",
    "identifier": "HB 723",
    "title": "Technology Coalitions Strategic Support Fund.",
    "updated": "",
    "core_ai_hits": 1,
    "adjacent_ai_hits": 0,
    "matched_concepts": [
      "artificial_intelligence"
    ],
    "matched_tiers": [
      "core_ai"
    ],
    "match_fields": [
      "raw_text"
    ],
    "in_ncsl": true,
    "source_bucket": "regex_flagged",
    "primary_url": "https://www.ncleg.gov/Sessions/2025/Bills/House/PDF/H723v0.pdf",
    "latest_action_date": "2025-04-03",
    "latest_action_description": "Ref to the Com on Appropriations, if favorable, Rules, Calendar, and Operations of the House",
    "ncsl_status": ""
  },
  {
    "bill_id": "ocd-bill/6a7a1aae-ec70-428f-8d86-bb4c9d06c889",
    "state": "NC",
    "session": "2025",
    "identifier": "HB 860",
    "title": "Social Media Control in Information Technology Act.",
    "updated": "",
    "core_ai_hits": 4,
    "adjacent_ai_hits": 2,
    "matched_concepts": [
      "generative_ai_variant",
      "algorithmic_tool",
      "adjacent_tech",
      "artificial_intelligence",
      "machine_learning"
    ],
    "matched_tiers": [
      "core_ai",
      "adjacent_ai"
    ],
    "match_fields": [
      "raw_text"
    ],
    "in_ncsl": false,
    "source_bucket": "regex_flagged",
    "primary_url": "https://www.ncleg.gov/Sessions/2025/Bills/House/PDF/H860v0.pdf",
    "latest_action_date": "2025-06-17",
    "latest_action_description": "Re-ref Com On Appropriations",
    "ncsl_status": ""
  },
  {
    "bill_id": "ocd-bill/45045399-970f-415c-b94d-cde3c457ed2b",
    "state": "NC",
    "session": "2019",
    "identifier": "HB 902",
    "title": "P&C Changes/Glob. Tranp./Prison Pilot.",
    "updated": "",
    "core_ai_hits": 1,
    "adjacent_ai_hits": 0,
    "matched_concepts": [
      "artificial_intelligence"
    ],
    "matched_tiers": [
      "core_ai"
    ],
    "match_fields": [
      "raw_text"
    ],
    "in_ncsl": false,
    "source_bucket": "regex_flagged",
    "primary_url": "http://www.ncleg.net/Sessions/2019/Bills/House/PDF/H902v6.pdf",
    "latest_action_date": "2020-07-02",
    "latest_action_description": "Ch. SL 2020-90",
    "ncsl_status": ""
  },
  {
    "bill_id": "ocd-bill/f9f95128-aa72-4608-b25a-a3d6bbd4810a",
    "state": "NC",
    "session": "2025",
    "identifier": "HB 934",
    "title": "Artificial Intelligence Regulatory Reform Act.",
    "updated": "",
    "core_ai_hits": 2,
    "adjacent_ai_hits": 0,
    "matched_concepts": [
      "deepfake_media",
      "artificial_intelligence"
    ],
    "matched_tiers": [
      "core_ai"
    ],
    "match_fields": [
      "title",
      "raw_text"
    ],
    "in_ncsl": true,
    "source_bucket": "regex_flagged",
    "primary_url": "https://www.ncleg.gov/Sessions/2025/Bills/House/PDF/H934v0.pdf",
    "latest_action_date": "2025-05-06",
    "latest_action_description": "Re-ref Com On Election Law",
    "ncsl_status": ""
  },
  {
    "bill_id": "ocd-bill/947c17f1-c7bf-45d3-89c3-ccd655f2226c",
    "state": "NC",
    "session": "2021",
    "identifier": "HB 937",
    "title": "Automatic Police Body Cam Analysis.",
    "updated": "",
    "core_ai_hits": 2,
    "adjacent_ai_hits": 2,
    "matched_concepts": [
      "machine_learning",
      "artificial_intelligence",
      "adjacent_tech"
    ],
    "matched_tiers": [
      "core_ai",
      "adjacent_ai"
    ],
    "match_fields": [
      "raw_text"
    ],
    "in_ncsl": true,
    "source_bucket": "regex_flagged",
    "primary_url": "https://www.ncleg.gov/Sessions/2021/Bills/House/PDF/H937v0.pdf",
    "latest_action_date": "2021-05-12",
    "latest_action_description": "Ref To Com On Rules, Calendar, and Operations of the House",
    "ncsl_status": ""
  },
  {
    "bill_id": "ocd-bill/d9e46364-1584-4a8a-8667-b4b24cebb7bf",
    "state": "NC",
    "session": "2025",
    "identifier": "HB 970",
    "title": "Preventing Algorithmic Rent Fixing.",
    "updated": "",
    "core_ai_hits": 2,
    "adjacent_ai_hits": 1,
    "matched_concepts": [
      "machine_learning",
      "artificial_intelligence"
    ],
    "matched_tiers": [
      "core_ai",
      "adjacent_ai"
    ],
    "match_fields": [
      "raw_text"
    ],
    "in_ncsl": true,
    "source_bucket": "regex_flagged",
    "primary_url": "https://www.ncleg.gov/Sessions/2025/Bills/House/PDF/H970v0.pdf",
    "latest_action_date": "2025-04-14",
    "latest_action_description": "Ref To Com On Rules, Calendar, and Operations of the House",
    "ncsl_status": ""
  },
  {
    "bill_id": "ocd-bill/f1765a3d-54cd-4e5e-bf4a-21f53b300390",
    "state": "NC",
    "session": "2023",
    "identifier": "HB 986",
    "title": "UNC Artificial Intelligence Hubs.",
    "updated": "",
    "core_ai_hits": 1,
    "adjacent_ai_hits": 0,
    "matched_concepts": [
      "artificial_intelligence"
    ],
    "matched_tiers": [
      "core_ai"
    ],
    "match_fields": [
      "title",
      "raw_text"
    ],
    "in_ncsl": true,
    "source_bucket": "regex_flagged",
    "primary_url": "https://www.ncleg.gov/Sessions/2023/Bills/House/PDF/H986v0.pdf",
    "latest_action_date": "2024-05-06",
    "latest_action_description": "Ref to the Com on Appropriations, if favorable, Rules, Calendar, and Operations of the House",
    "ncsl_status": ""
  },
  {
    "bill_id": "ocd-bill/38e9df54-385d-47d8-906a-49d276464851",
    "state": "NC",
    "session": "2025",
    "identifier": "SB 287",
    "title": "Safeguard Health Ins. Utilization Reviews.",
    "updated": "",
    "core_ai_hits": 1,
    "adjacent_ai_hits": 0,
    "matched_concepts": [
      "artificial_intelligence"
    ],
    "matched_tiers": [
      "core_ai"
    ],
    "match_fields": [
      "raw_text"
    ],
    "in_ncsl": true,
    "source_bucket": "regex_flagged",
    "primary_url": "https://www.ncleg.gov/Sessions/2025/Bills/Senate/PDF/S287v0.pdf",
    "latest_action_date": "2025-03-17",
    "latest_action_description": "Ref To Com On Rules and Operations of the Senate",
    "ncsl_status": ""
  },
  {
    "bill_id": "ocd-bill/8a458ea6-10c7-4875-bbd6-5e119f2093a6",
    "state": "NC",
    "session": "2025",
    "identifier": "SB 315",
    "title": "More Transparency/Efficiency in Utiliz. Rev.",
    "updated": "",
    "core_ai_hits": 1,
    "adjacent_ai_hits": 0,
    "matched_concepts": [
      "artificial_intelligence"
    ],
    "matched_tiers": [
      "core_ai"
    ],
    "match_fields": [
      "raw_text"
    ],
    "in_ncsl": true,
    "source_bucket": "regex_flagged",
    "primary_url": "https://www.ncleg.gov/Sessions/2025/Bills/Senate/PDF/S315v0.pdf",
    "latest_action_date": "2025-03-18",
    "latest_action_description": "Ref to Health Care.  If fav, re-ref to Rules and Operations of the Senate",
    "ncsl_status": ""
  },
  {
    "bill_id": "ocd-bill/960c0fc5-047d-4286-8d45-8b8fabc3b11a",
    "state": "NC",
    "session": "2023",
    "identifier": "SB 382",
    "title": "Disaster Relief-3/Budget/Various Law Changes.",
    "updated": "",
    "core_ai_hits": 3,
    "adjacent_ai_hits": 1,
    "matched_concepts": [
      "ai_system_composite",
      "artificial_intelligence",
      "ai_system"
    ],
    "matched_tiers": [
      "adjacent_ai",
      "core_ai"
    ],
    "match_fields": [
      "raw_text"
    ],
    "in_ncsl": false,
    "source_bucket": "regex_flagged",
    "primary_url": "https://www.ncleg.gov/Sessions/2023/Bills/Senate/PDF/S382v4.pdf",
    "latest_action_date": "2024-12-11",
    "latest_action_description": "Ch. SL 2024-57",
    "ncsl_status": ""
  },
  {
    "bill_id": "ocd-bill/bfd0390a-807a-499e-8a45-0f9ca486fe52",
    "state": "NC",
    "session": "2023",
    "identifier": "SB 460",
    "title": "Study Automation and the Workforce.",
    "updated": "",
    "core_ai_hits": 1,
    "adjacent_ai_hits": 0,
    "matched_concepts": [
      "artificial_intelligence"
    ],
    "matched_tiers": [
      "core_ai"
    ],
    "match_fields": [
      "raw_text"
    ],
    "in_ncsl": true,
    "source_bucket": "regex_flagged",
    "primary_url": "https://www.ncleg.gov/Sessions/2023/Bills/Senate/PDF/S460v0.pdf",
    "latest_action_date": "2023-04-03",
    "latest_action_description": "Ref To Com On Rules and Operations of the Senate",
    "ncsl_status": ""
  },
  {
    "bill_id": "ocd-bill/5c584750-641c-401c-94bd-fe092a782c07",
    "state": "NC",
    "session": "2025",
    "identifier": "SB 483",
    "title": "The Children First Act.",
    "updated": "",
    "core_ai_hits": 1,
    "adjacent_ai_hits": 0,
    "matched_concepts": [
      "artificial_intelligence"
    ],
    "matched_tiers": [
      "core_ai"
    ],
    "match_fields": [
      "raw_text"
    ],
    "in_ncsl": true,
    "source_bucket": "regex_flagged",
    "primary_url": "https://www.ncleg.gov/Sessions/2025/Bills/Senate/PDF/S483v0.pdf",
    "latest_action_date": "2025-03-26",
    "latest_action_description": "Ref To Com On Rules and Operations of the Senate",
    "ncsl_status": ""
  },
  {
    "bill_id": "ocd-bill/e62271be-0e5f-406b-aed6-c5e3227d2917",
    "state": "NC",
    "session": "2025",
    "identifier": "SB 514",
    "title": "Social Media Control in IT Act.",
    "updated": "",
    "core_ai_hits": 4,
    "adjacent_ai_hits": 2,
    "matched_concepts": [
      "artificial_intelligence",
      "machine_learning",
      "adjacent_tech",
      "generative_ai_variant",
      "algorithmic_tool"
    ],
    "matched_tiers": [
      "core_ai",
      "adjacent_ai"
    ],
    "match_fields": [
      "raw_text"
    ],
    "in_ncsl": true,
    "source_bucket": "regex_flagged",
    "primary_url": "https://www.ncleg.gov/Sessions/2025/Bills/Senate/PDF/S514v0.pdf",
    "latest_action_date": "2025-04-01",
    "latest_action_description": "Re-ref Com On Appropriations/Base Budget",
    "ncsl_status": ""
  },
  {
    "bill_id": "ocd-bill/86380f47-6f92-4041-b112-efd4cbfd1ad8",
    "state": "NC",
    "session": "2025",
    "identifier": "SB 579",
    "title": "Transforming the High School Experience.",
    "updated": "",
    "core_ai_hits": 1,
    "adjacent_ai_hits": 0,
    "matched_concepts": [
      "artificial_intelligence"
    ],
    "matched_tiers": [
      "core_ai"
    ],
    "match_fields": [
      "raw_text"
    ],
    "in_ncsl": true,
    "source_bucket": "regex_flagged",
    "primary_url": "https://www.ncleg.gov/Sessions/2025/Bills/Senate/PDF/S579v0.pdf",
    "latest_action_date": "2025-04-30",
    "latest_action_description": "Re-ref Com On Rules and Operations of the Senate",
    "ncsl_status": ""
  },
  {
    "bill_id": "ocd-bill/034932c6-7e92-4499-aada-a1b9aeda5836",
    "state": "NC",
    "session": "2021",
    "identifier": "SB 600",
    "title": "Study Automation and the Workforce.",
    "updated": "",
    "core_ai_hits": 1,
    "adjacent_ai_hits": 0,
    "matched_concepts": [
      "artificial_intelligence"
    ],
    "matched_tiers": [
      "core_ai"
    ],
    "match_fields": [
      "raw_text"
    ],
    "in_ncsl": true,
    "source_bucket": "regex_flagged",
    "primary_url": "https://www.ncleg.gov/Sessions/2021/Bills/Senate/PDF/S600v0.pdf",
    "latest_action_date": "2021-04-07",
    "latest_action_description": "Ref To Com On Rules and Operations of the Senate",
    "ncsl_status": ""
  },
  {
    "bill_id": "ocd-bill/d09cfcd4-dfad-47bb-a9b6-a70bdc398440",
    "state": "NC",
    "session": "2025",
    "identifier": "SB 619",
    "title": "AI Academic Support Grant Program.",
    "updated": "",
    "core_ai_hits": 1,
    "adjacent_ai_hits": 0,
    "matched_concepts": [
      "artificial_intelligence"
    ],
    "matched_tiers": [
      "core_ai"
    ],
    "match_fields": [
      "raw_text"
    ],
    "in_ncsl": true,
    "source_bucket": "regex_flagged",
    "primary_url": "https://www.ncleg.gov/Sessions/2025/Bills/Senate/PDF/S619v0.pdf",
    "latest_action_date": "2025-03-26",
    "latest_action_description": "Re-ref Com On Appropriations/Base Budget",
    "ncsl_status": ""
  },
  {
    "bill_id": "ocd-bill/f62fd260-3ea7-437b-8b92-3a311e52f085",
    "state": "NC",
    "session": "2025",
    "identifier": "SB 624",
    "title": "AI Chatbots - Licensing/Safety/Privacy.",
    "updated": "",
    "core_ai_hits": 5,
    "adjacent_ai_hits": 2,
    "matched_concepts": [
      "artificial_intelligence",
      "ml_system",
      "machine_learning",
      "generative_ai_variant",
      "adjacent_tech",
      "ai_system_composite"
    ],
    "matched_tiers": [
      "adjacent_ai",
      "core_ai"
    ],
    "match_fields": [
      "raw_text"
    ],
    "in_ncsl": true,
    "source_bucket": "regex_flagged",
    "primary_url": "https://www.ncleg.gov/Sessions/2025/Bills/Senate/PDF/S624v0.pdf",
    "latest_action_date": "2025-03-26",
    "latest_action_description": "Ref To Com On Rules and Operations of the Senate",
    "ncsl_status": ""
  },
  {
    "bill_id": "ocd-bill/716505e0-b441-47de-9f89-7fea3cf68888",
    "state": "NC",
    "session": "2025",
    "identifier": "SB 640",
    "title": "AI Ethics and Literacy Across Education.",
    "updated": "",
    "core_ai_hits": 4,
    "adjacent_ai_hits": 2,
    "matched_concepts": [
      "artificial_intelligence",
      "ai_system",
      "adjacent_tech",
      "ai_system_composite",
      "ai_model_variant"
    ],
    "matched_tiers": [
      "core_ai",
      "adjacent_ai"
    ],
    "match_fields": [
      "raw_text",
      "title"
    ],
    "in_ncsl": true,
    "source_bucket": "regex_flagged",
    "primary_url": "https://www.ncleg.gov/Sessions/2025/Bills/Senate/PDF/S640v0.pdf",
    "latest_action_date": "2025-03-26",
    "latest_action_description": "Ref To Com On Rules and Operations of the Senate",
    "ncsl_status": ""
  },
  {
    "bill_id": "ocd-bill/355044c5-5ab0-487c-b480-8866657b5675",
    "state": "NC",
    "session": "2023",
    "identifier": "SB 684",
    "title": "Stormwater Program Revisions.",
    "updated": "",
    "core_ai_hits": 2,
    "adjacent_ai_hits": 2,
    "matched_concepts": [
      "artificial_intelligence",
      "machine_learning"
    ],
    "matched_tiers": [
      "core_ai",
      "adjacent_ai"
    ],
    "match_fields": [
      "raw_text"
    ],
    "in_ncsl": true,
    "source_bucket": "regex_flagged",
    "primary_url": "https://www.ncleg.gov/Sessions/2023/Bills/Senate/PDF/S684v0.pdf",
    "latest_action_date": "2023-04-13",
    "latest_action_description": "Re-ref to Agriculture, Energy, and Environment.  If fav, re-ref to Appropriations/Base Budget.  If fav, re-ref to Rules and Operations of the Senate",
    "ncsl_status": ""
  },
  {
    "bill_id": "ocd-bill/8cf91cd7-7481-4156-82fb-283bd026d576",
    "state": "NC",
    "session": "2025",
    "identifier": "SB 722",
    "title": "Children's Online Safety Act/Funds.",
    "updated": "",
    "core_ai_hits": 1,
    "adjacent_ai_hits": 0,
    "matched_concepts": [
      "algorithmic_decision_system"
    ],
    "matched_tiers": [
      "core_ai"
    ],
    "match_fields": [
      "raw_text"
    ],
    "in_ncsl": false,
    "source_bucket": "regex_flagged",
    "primary_url": "https://www.ncleg.gov/Sessions/2025/Bills/Senate/PDF/S722v0.pdf",
    "latest_action_date": "2025-03-26",
    "latest_action_description": "Re-ref Com On Appropriations/Base Budget",
    "ncsl_status": ""
  },
  {
    "bill_id": "ocd-bill/b3f7d366-1eae-4ff8-b6b3-dc29d1a37eaf",
    "state": "NC",
    "session": "2025",
    "identifier": "SB 735",
    "title": "AI Innovation Trust Fund.",
    "updated": "",
    "core_ai_hits": 5,
    "adjacent_ai_hits": 1,
    "matched_concepts": [
      "adjacent_tech",
      "ai_system_composite",
      "ai_model_variant",
      "artificial_intelligence",
      "ai_governance",
      "ai_system"
    ],
    "matched_tiers": [
      "adjacent_ai",
      "core_ai"
    ],
    "match_fields": [
      "raw_text"
    ],
    "in_ncsl": true,
    "source_bucket": "regex_flagged",
    "primary_url": "https://www.ncleg.gov/Sessions/2025/Bills/Senate/PDF/S735v0.pdf",
    "latest_action_date": "2025-03-26",
    "latest_action_description": "Re-ref Com On Appropriations/Base Budget",
    "ncsl_status": ""
  },
  {
    "bill_id": "ocd-bill/31b5941c-4db4-493f-92b6-bdde4919cdc8",
    "state": "NC",
    "session": "2025",
    "identifier": "SB 738",
    "title": "Digital Content Provenance Initiative/Funds.",
    "updated": "",
    "core_ai_hits": 3,
    "adjacent_ai_hits": 1,
    "matched_concepts": [
      "machine_learning",
      "artificial_intelligence",
      "synthetic_media"
    ],
    "matched_tiers": [
      "adjacent_ai",
      "core_ai"
    ],
    "match_fields": [
      "raw_text"
    ],
    "in_ncsl": true,
    "source_bucket": "regex_flagged",
    "primary_url": "https://www.ncleg.gov/Sessions/2025/Bills/Senate/PDF/S738v0.pdf",
    "latest_action_date": "2025-03-26",
    "latest_action_description": "Re-ref Com On Appropriations/Base Budget",
    "ncsl_status": ""
  },
  {
    "bill_id": "ocd-bill/2cb68e73-76fa-4d28-a401-976cfd9051e7",
    "state": "NC",
    "session": "2025",
    "identifier": "SB 746",
    "title": "Study Automation and the Workforce.",
    "updated": "",
    "core_ai_hits": 1,
    "adjacent_ai_hits": 0,
    "matched_concepts": [
      "artificial_intelligence"
    ],
    "matched_tiers": [
      "core_ai"
    ],
    "match_fields": [
      "raw_text"
    ],
    "in_ncsl": true,
    "source_bucket": "regex_flagged",
    "primary_url": "https://www.ncleg.gov/Sessions/2025/Bills/Senate/PDF/S746v0.pdf",
    "latest_action_date": "2025-03-26",
    "latest_action_description": "Ref To Com On Rules and Operations of the Senate",
    "ncsl_status": ""
  },
  {
    "bill_id": "ocd-bill/a71a1903-28fe-4c54-b121-e25541c236f1",
    "state": "NC",
    "session": "2025",
    "identifier": "SB 747",
    "title": "AI Learning Agenda.",
    "updated": "",
    "core_ai_hits": 2,
    "adjacent_ai_hits": 1,
    "matched_concepts": [
      "artificial_intelligence",
      "ai_system_composite"
    ],
    "matched_tiers": [
      "adjacent_ai",
      "core_ai"
    ],
    "match_fields": [
      "raw_text"
    ],
    "in_ncsl": true,
    "source_bucket": "regex_flagged",
    "primary_url": "https://www.ncleg.gov/Sessions/2025/Bills/Senate/PDF/S747v0.pdf",
    "latest_action_date": "2025-03-26",
    "latest_action_description": "Ref To Com On Rules and Operations of the Senate",
    "ncsl_status": ""
  },
  {
    "bill_id": "ocd-bill/016854f9-6f5d-430d-9589-0174a8830ada",
    "state": "NC",
    "session": "2021",
    "identifier": "SB 795",
    "title": "Inmate and Youth Offender Tracking Technology.",
    "updated": "",
    "core_ai_hits": 1,
    "adjacent_ai_hits": 0,
    "matched_concepts": [
      "artificial_intelligence"
    ],
    "matched_tiers": [
      "core_ai"
    ],
    "match_fields": [
      "raw_text"
    ],
    "in_ncsl": true,
    "source_bucket": "regex_flagged",
    "primary_url": "https://www.ncleg.gov/Sessions/2021/Bills/Senate/PDF/S795v0.pdf",
    "latest_action_date": "2022-05-26",
    "latest_action_description": "Ref to Appropriations/Base Budget.  If fav, re-ref to Rules and Operations of the Senate",
    "ncsl_status": ""
  },
  {
    "bill_id": "ocd-bill/319010c4-aa48-4f50-b5a7-abc8dde90ea2",
    "state": "NC",
    "session": "2023",
    "identifier": "SB 828",
    "title": "Child Protection and Deepfake Prohibition Act.",
    "updated": "",
    "core_ai_hits": 1,
    "adjacent_ai_hits": 0,
    "matched_concepts": [
      "deepfake_media"
    ],
    "matched_tiers": [
      "core_ai"
    ],
    "match_fields": [
      "title",
      "raw_text"
    ],
    "in_ncsl": false,
    "source_bucket": "regex_flagged",
    "primary_url": "https://www.ncleg.gov/Sessions/2023/Bills/Senate/PDF/S828v0.pdf",
    "latest_action_date": "2024-05-06",
    "latest_action_description": "Ref To Com On Rules and Operations of the Senate",
    "ncsl_status": ""
  },
  {
    "bill_id": "ocd-bill/5d77337f-7581-40cc-9567-44060938c2c1",
    "state": "NC",
    "session": "2023",
    "identifier": "SB 880",
    "title": "No Deepfakes in Election Communication.",
    "updated": "",
    "core_ai_hits": 3,
    "adjacent_ai_hits": 0,
    "matched_concepts": [
      "deepfake_media",
      "artificial_intelligence",
      "synthetic_media"
    ],
    "matched_tiers": [
      "core_ai"
    ],
    "match_fields": [
      "raw_text",
      "title"
    ],
    "in_ncsl": true,
    "source_bucket": "regex_flagged",
    "primary_url": "https://www.ncleg.gov/Sessions/2023/Bills/Senate/PDF/S880v0.pdf",
    "latest_action_date": "2024-05-06",
    "latest_action_description": "Ref To Com On Rules and Operations of the Senate",
    "ncsl_status": ""
  }
]