[
  {
    "bill_id": "",
    "state": "OH",
    "session": "2025",
    "identifier": "H 84",
    "title": "",
    "updated": "",
    "core_ai_hits": 0,
    "adjacent_ai_hits": 0,
    "matched_concepts": [
      "ncsl_curated_ai_law"
    ],
    "matched_tiers": [
      "ncsl"
    ],
    "match_fields": [
      "ncsl_source"
    ],
    "in_ncsl": true,
    "source_bucket": "ncsl_only",
    "primary_url": "http://custom.statenet.com/public/resources.cgi?id=ID:bill:OH2025000H84&ciq=urn:user:PA196471263&client_md=67f0cff791bea21b5da07dbe9779ac01&mode=current_text",
    "latest_action_date": "",
    "latest_action_description": "",
    "ncsl_status": ""
  },
  {
    "bill_id": "ocd-bill/b2c93b54-e177-46d2-a79b-3dfd0ccc2c72",
    "state": "OH",
    "session": "136",
    "identifier": "HB 106",
    "title": "Enact Alyssa's Law",
    "updated": "",
    "core_ai_hits": 1,
    "adjacent_ai_hits": 0,
    "matched_concepts": [
      "artificial_intelligence"
    ],
    "matched_tiers": [
      "core_ai"
    ],
    "match_fields": [
      "raw_text",
      "abstract"
    ],
    "in_ncsl": true,
    "source_bucket": "regex_flagged",
    "primary_url": "https://search-prod.lis.state.oh.us/api/v2/general_assembly_136/legislation/hb106/00_IN/pdf/",
    "latest_action_date": "2025-02-26T05:00:00+00:00",
    "latest_action_description": "Referred to committee",
    "ncsl_status": ""
  },
  {
    "bill_id": "ocd-bill/6fd6a079-2022-4820-b9cb-42b14c78783c",
    "state": "OH",
    "session": "134",
    "identifier": "HB 110",
    "title": "Creates appropriations for FY 2022-2023.",
    "updated": "",
    "core_ai_hits": 1,
    "adjacent_ai_hits": 1,
    "matched_concepts": [
      "artificial_intelligence",
      "adjacent_tech"
    ],
    "matched_tiers": [
      "core_ai",
      "adjacent_ai"
    ],
    "match_fields": [
      "raw_text"
    ],
    "in_ncsl": true,
    "source_bucket": "regex_flagged",
    "primary_url": "https://search-prod.lis.state.oh.us/solarapi/v1/general_assembly_134/bills/hb110/RS/04/hb110_04_RS?format=pdf",
    "latest_action_date": "2021-11-01",
    "latest_action_description": "line item veto receipt",
    "ncsl_status": ""
  },
  {
    "bill_id": "ocd-bill/1a2e0c0c-6069-4e90-8947-360bb8b86f0a",
    "state": "OH",
    "session": "135",
    "identifier": "HB 12",
    "title": "Rename and revise duties of Department of Education and Workforce",
    "updated": "",
    "core_ai_hits": 0,
    "adjacent_ai_hits": 1,
    "matched_concepts": [
      "adjacent_tech"
    ],
    "matched_tiers": [
      "adjacent_ai"
    ],
    "match_fields": [
      "raw_text"
    ],
    "in_ncsl": false,
    "source_bucket": "regex_flagged",
    "primary_url": "https://search-prod.lis.state.oh.us/solarapi/v1/general_assembly_135/bills/hb12/IN/00/hb12_00_IN?format=pdf",
    "latest_action_date": "2023-02-16",
    "latest_action_description": "Refer to Committee",
    "ncsl_status": ""
  },
  {
    "bill_id": "ocd-bill/dc938344-1eed-4df3-9a6f-28b9b5e5ca17",
    "state": "OH",
    "session": "136",
    "identifier": "HB 185",
    "title": "Regards an individual's persona usage; prohibit certain deepfakes",
    "updated": "",
    "core_ai_hits": 1,
    "adjacent_ai_hits": 0,
    "matched_concepts": [
      "deepfake_media"
    ],
    "matched_tiers": [
      "core_ai"
    ],
    "match_fields": [
      "abstract",
      "raw_text",
      "title"
    ],
    "in_ncsl": true,
    "source_bucket": "regex_flagged",
    "primary_url": "https://search-prod.lis.state.oh.us/api/v2/general_assembly_136/legislation/hb185/00_IN/pdf/",
    "latest_action_date": "2025-03-26T04:00:00+00:00",
    "latest_action_description": "Referred to committee",
    "ncsl_status": ""
  },
  {
    "bill_id": "ocd-bill/b627b6f3-e63d-4640-bbab-3ca5005972e5",
    "state": "OH",
    "session": "134",
    "identifier": "HB 205",
    "title": "Enact Collin's Law: The \"Ohio Anti-Bullying and Hazing Act\"",
    "updated": "",
    "core_ai_hits": 0,
    "adjacent_ai_hits": 1,
    "matched_concepts": [
      "adjacent_tech"
    ],
    "matched_tiers": [
      "adjacent_ai"
    ],
    "match_fields": [
      "raw_text"
    ],
    "in_ncsl": false,
    "source_bucket": "regex_flagged",
    "primary_url": "https://search-prod.lis.state.oh.us/solarapi/v1/general_assembly_134/bills/hb205/IN/00/hb205_00_IN?format=pdf",
    "latest_action_date": "2021-03-16",
    "latest_action_description": "Refer to Committee",
    "ncsl_status": ""
  },
  {
    "bill_id": "ocd-bill/f2ff1ded-4e36-4680-b494-b8d0ebd30f8d",
    "state": "OH",
    "session": "135",
    "identifier": "HB 206",
    "title": "Regards public school expulsion for actions dangerous to others",
    "updated": "",
    "core_ai_hits": 0,
    "adjacent_ai_hits": 1,
    "matched_concepts": [
      "adjacent_tech"
    ],
    "matched_tiers": [
      "adjacent_ai"
    ],
    "match_fields": [
      "raw_text"
    ],
    "in_ncsl": false,
    "source_bucket": "regex_flagged",
    "primary_url": "https://search-prod.lis.state.oh.us/solarapi/v1/general_assembly_135/bills/hb206/RS/03/hb206_03_RS?format=pdf",
    "latest_action_date": "2024-12-19",
    "latest_action_description": "Concurred in Senate amendments",
    "ncsl_status": ""
  },
  {
    "bill_id": "ocd-bill/8e60520a-4a48-4144-84a4-0eeca3cbc59f",
    "state": "OH",
    "session": "134",
    "identifier": "HB 296",
    "title": "Revise voter registration and conduct of elections",
    "updated": "",
    "core_ai_hits": 0,
    "adjacent_ai_hits": 1,
    "matched_concepts": [
      "adjacent_tech"
    ],
    "matched_tiers": [
      "adjacent_ai"
    ],
    "match_fields": [
      "raw_text"
    ],
    "in_ncsl": false,
    "source_bucket": "regex_flagged",
    "primary_url": "https://search-prod.lis.state.oh.us/solarapi/v1/general_assembly_134/bills/hb296/IN/00/hb296_00_IN?format=pdf",
    "latest_action_date": "2021-05-12",
    "latest_action_description": "Refer to Committee",
    "ncsl_status": ""
  },
  {
    "bill_id": "ocd-bill/21e00fd0-8be9-4754-a93a-ff0162ea99b5",
    "state": "OH",
    "session": "136",
    "identifier": "HB 321",
    "title": "Revise Unemployment Compensation Law",
    "updated": "",
    "core_ai_hits": 0,
    "adjacent_ai_hits": 1,
    "matched_concepts": [
      "adjacent_tech"
    ],
    "matched_tiers": [
      "adjacent_ai"
    ],
    "match_fields": [
      "raw_text"
    ],
    "in_ncsl": false,
    "source_bucket": "regex_flagged",
    "primary_url": "https://search-prod.lis.state.oh.us/api/v2/general_assembly_136/legislation/hb321/00_IN/pdf/",
    "latest_action_date": "2025-06-04T04:00:00+00:00",
    "latest_action_description": "Referred to committee",
    "ncsl_status": ""
  },
  {
    "bill_id": "ocd-bill/14a66dde-0c5a-4c8a-bcd7-ab929060cd3f",
    "state": "OH",
    "session": "135",
    "identifier": "HB 33",
    "title": "Establishes operating appropriations for fiscal years 2024-2025",
    "updated": "",
    "core_ai_hits": 0,
    "adjacent_ai_hits": 1,
    "matched_concepts": [
      "adjacent_tech"
    ],
    "matched_tiers": [
      "adjacent_ai"
    ],
    "match_fields": [
      "raw_text"
    ],
    "in_ncsl": false,
    "source_bucket": "regex_flagged",
    "primary_url": "https://search-prod.lis.state.oh.us/solarapi/v1/general_assembly_135/bills/hb33/RS/03/hb33_03_RS?format=pdf",
    "latest_action_date": "2024-01-24",
    "latest_action_description": "Item passed notwithstanding objections of the Governor",
    "ncsl_status": ""
  },
  {
    "bill_id": "ocd-bill/d9331967-d98c-4635-9f2c-251b5e6ec3d7",
    "state": "OH",
    "session": "136",
    "identifier": "HB 362",
    "title": "Regulate fraudulent synthetic media for influencing elections",
    "updated": "",
    "core_ai_hits": 2,
    "adjacent_ai_hits": 0,
    "matched_concepts": [
      "synthetic_media",
      "artificial_intelligence"
    ],
    "matched_tiers": [
      "core_ai"
    ],
    "match_fields": [
      "abstract",
      "title",
      "raw_text"
    ],
    "in_ncsl": true,
    "source_bucket": "regex_flagged",
    "primary_url": "https://search-prod.lis.state.oh.us/api/v2/general_assembly_136/legislation/hb362/00_IN/pdf/",
    "latest_action_date": "2025-06-18T04:00:00+00:00",
    "latest_action_description": "Referred to committee",
    "ncsl_status": ""
  },
  {
    "bill_id": "ocd-bill/c953a267-127e-4af8-b3d0-09916b441964",
    "state": "OH",
    "session": "135",
    "identifier": "HB 367",
    "title": "Regards unauthorized use of an individual's persona, deepfakes",
    "updated": "",
    "core_ai_hits": 1,
    "adjacent_ai_hits": 0,
    "matched_concepts": [
      "deepfake_media"
    ],
    "matched_tiers": [
      "core_ai"
    ],
    "match_fields": [
      "title",
      "raw_text"
    ],
    "in_ncsl": false,
    "source_bucket": "regex_flagged",
    "primary_url": "https://search-prod.lis.state.oh.us/solarapi/v1/general_assembly_135/bills/hb367/RH/01/hb367_01_RH?format=pdf",
    "latest_action_date": "2024-06-11",
    "latest_action_description": "Reported",
    "ncsl_status": ""
  },
  {
    "bill_id": "ocd-bill/67bbfc23-1730-40e1-b588-e230c2d03a3b",
    "state": "OH",
    "session": "136",
    "identifier": "HB 392",
    "title": "Enact the Ohio Right to Compute Act",
    "updated": "",
    "core_ai_hits": 4,
    "adjacent_ai_hits": 1,
    "matched_concepts": [
      "artificial_intelligence",
      "machine_learning",
      "ai_system_composite",
      "deepfake_media"
    ],
    "matched_tiers": [
      "core_ai",
      "adjacent_ai"
    ],
    "match_fields": [
      "raw_text"
    ],
    "in_ncsl": true,
    "source_bucket": "regex_flagged",
    "primary_url": "https://search-prod.lis.state.oh.us/api/v2/general_assembly_136/legislation/hb392/00_IN/pdf/",
    "latest_action_date": "2025-09-15T04:00:00+00:00",
    "latest_action_description": "Referred to committee",
    "ncsl_status": ""
  },
  {
    "bill_id": "ocd-bill/b9255bcd-77df-40c7-9646-01bbbbfa30e9",
    "state": "OH",
    "session": "135",
    "identifier": "HB 401",
    "title": "Create the offense of nonconsensual distribution of a deepfake",
    "updated": "",
    "core_ai_hits": 1,
    "adjacent_ai_hits": 0,
    "matched_concepts": [
      "deepfake_media"
    ],
    "matched_tiers": [
      "core_ai"
    ],
    "match_fields": [
      "raw_text",
      "title"
    ],
    "in_ncsl": false,
    "source_bucket": "regex_flagged",
    "primary_url": "https://search-prod.lis.state.oh.us/solarapi/v1/general_assembly_135/bills/hb401/IN/00/hb401_00_IN?format=pdf",
    "latest_action_date": "2024-04-02",
    "latest_action_description": "Refer to Committee",
    "ncsl_status": ""
  },
  {
    "bill_id": "ocd-bill/5bdbd903-372b-4d81-b6ad-7208caeec523",
    "state": "OH",
    "session": "135",
    "identifier": "HB 410",
    "title": "Regulate dissemination of deepfake media to influence an election",
    "updated": "",
    "core_ai_hits": 1,
    "adjacent_ai_hits": 0,
    "matched_concepts": [
      "deepfake_media"
    ],
    "matched_tiers": [
      "core_ai"
    ],
    "match_fields": [
      "title",
      "raw_text"
    ],
    "in_ncsl": false,
    "source_bucket": "regex_flagged",
    "primary_url": "https://search-prod.lis.state.oh.us/solarapi/v1/general_assembly_135/bills/hb410/IN/00/hb410_00_IN?format=pdf",
    "latest_action_date": "2024-04-02",
    "latest_action_description": "Refer to Committee",
    "ncsl_status": ""
  },
  {
    "bill_id": "ocd-bill/7a538be2-17e5-4968-b57c-4ae5255465e3",
    "state": "OH",
    "session": "136",
    "identifier": "HB 455",
    "title": "Regards the operation of public schools and the DEW",
    "updated": "",
    "core_ai_hits": 1,
    "adjacent_ai_hits": 0,
    "matched_concepts": [
      "artificial_intelligence"
    ],
    "matched_tiers": [
      "core_ai"
    ],
    "match_fields": [
      "raw_text"
    ],
    "in_ncsl": true,
    "source_bucket": "regex_flagged",
    "primary_url": "https://search-prod.lis.state.oh.us/api/v2/general_assembly_136/legislation/hb455/01_RH/pdf/",
    "latest_action_date": "2026-02-11T05:00:00+00:00",
    "latest_action_description": "Referred to committee",
    "ncsl_status": ""
  },
  {
    "bill_id": "ocd-bill/5253611f-9a61-41be-b685-896ae5a28e2b",
    "state": "OH",
    "session": "136",
    "identifier": "HB 469",
    "title": "Declare A.I. systems nonsentient; prohibit legal personhood",
    "updated": "",
    "core_ai_hits": 4,
    "adjacent_ai_hits": 0,
    "matched_concepts": [
      "generative_ai_variant",
      "ai_system_composite",
      "artificial_intelligence",
      "ai_system"
    ],
    "matched_tiers": [
      "core_ai"
    ],
    "match_fields": [
      "abstract",
      "raw_text"
    ],
    "in_ncsl": true,
    "source_bucket": "regex_flagged",
    "primary_url": "https://search-prod.lis.state.oh.us/api/v2/general_assembly_136/legislation/hb469/00_IN/pdf/",
    "latest_action_date": "2025-10-01T04:00:00+00:00",
    "latest_action_description": "Referred to committee",
    "ncsl_status": ""
  },
  {
    "bill_id": "ocd-bill/a73473a2-7dc7-49d2-ae2c-86841f930183",
    "state": "OH",
    "session": "135",
    "identifier": "HB 472",
    "title": "Regards voter registration, voting, and voting systems",
    "updated": "",
    "core_ai_hits": 0,
    "adjacent_ai_hits": 1,
    "matched_concepts": [
      "adjacent_tech"
    ],
    "matched_tiers": [
      "adjacent_ai"
    ],
    "match_fields": [
      "raw_text"
    ],
    "in_ncsl": false,
    "source_bucket": "regex_flagged",
    "primary_url": "https://search-prod.lis.state.oh.us/solarapi/v1/general_assembly_135/bills/hb472/IN/00/hb472_00_IN?format=pdf",
    "latest_action_date": "2024-04-23",
    "latest_action_description": "Refer to Committee",
    "ncsl_status": ""
  },
  {
    "bill_id": "ocd-bill/b9837b1c-6517-4c2a-9b08-54adf7d4bf45",
    "state": "OH",
    "session": "136",
    "identifier": "HB 524",
    "title": "Impose penalties for AI models suggesting harming self or another",
    "updated": "",
    "core_ai_hits": 3,
    "adjacent_ai_hits": 0,
    "matched_concepts": [
      "ai_system_composite",
      "ai_model_variant",
      "artificial_intelligence"
    ],
    "matched_tiers": [
      "core_ai"
    ],
    "match_fields": [
      "abstract",
      "title",
      "raw_text"
    ],
    "in_ncsl": false,
    "source_bucket": "regex_flagged",
    "primary_url": "https://search-prod.lis.state.oh.us/api/v2/general_assembly_136/legislation/hb524/00_IN/pdf/",
    "latest_action_date": "2025-10-22T04:00:00+00:00",
    "latest_action_description": "Referred to committee",
    "ncsl_status": ""
  },
  {
    "bill_id": "ocd-bill/553e9ae5-6acd-4e54-962f-edd08ad28824",
    "state": "OH",
    "session": "136",
    "identifier": "HB 525",
    "title": "Regards use of artificial intelligence in therapy services",
    "updated": "",
    "core_ai_hits": 3,
    "adjacent_ai_hits": 0,
    "matched_concepts": [
      "artificial_intelligence",
      "ai_system_composite",
      "generative_ai_variant"
    ],
    "matched_tiers": [
      "core_ai"
    ],
    "match_fields": [
      "title",
      "abstract",
      "raw_text"
    ],
    "in_ncsl": true,
    "source_bucket": "regex_flagged",
    "primary_url": "https://search-prod.lis.state.oh.us/api/v2/general_assembly_136/legislation/hb525/00_IN/pdf/",
    "latest_action_date": "2025-10-22T04:00:00+00:00",
    "latest_action_description": "Referred to committee",
    "ncsl_status": ""
  },
  {
    "bill_id": "ocd-bill/d5dbf7b2-de8c-4c63-be58-efaf9d3edd50",
    "state": "OH",
    "session": "136",
    "identifier": "HB 579",
    "title": "Regulate the use of artificial intelligence by health insurers",
    "updated": "",
    "core_ai_hits": 1,
    "adjacent_ai_hits": 0,
    "matched_concepts": [
      "artificial_intelligence"
    ],
    "matched_tiers": [
      "core_ai"
    ],
    "match_fields": [
      "abstract",
      "title",
      "raw_text"
    ],
    "in_ncsl": true,
    "source_bucket": "regex_flagged",
    "primary_url": "https://search-prod.lis.state.oh.us/api/v2/general_assembly_136/legislation/hb579/00_IN/pdf/",
    "latest_action_date": "2025-11-12T05:00:00+00:00",
    "latest_action_description": "Referred to committee",
    "ncsl_status": ""
  },
  {
    "bill_id": "ocd-bill/596e9fce-587b-49e5-afcd-5f74025816c7",
    "state": "OH",
    "session": "136",
    "identifier": "HB 594",
    "title": "Require students complete a high school computer science course",
    "updated": "",
    "core_ai_hits": 1,
    "adjacent_ai_hits": 0,
    "matched_concepts": [
      "artificial_intelligence"
    ],
    "matched_tiers": [
      "core_ai"
    ],
    "match_fields": [
      "raw_text"
    ],
    "in_ncsl": true,
    "source_bucket": "regex_flagged",
    "primary_url": "https://search-prod.lis.state.oh.us/api/v2/general_assembly_136/legislation/hb594/00_IN/pdf/",
    "latest_action_date": "2025-11-19T05:00:00+00:00",
    "latest_action_description": "Referred to committee",
    "ncsl_status": ""
  },
  {
    "bill_id": "ocd-bill/efc33d20-c57a-48c7-bab7-1f987d6f7f8a",
    "state": "OH",
    "session": "134",
    "identifier": "HB 599",
    "title": "Enact Entertainment Technology Initiative",
    "updated": "",
    "core_ai_hits": 0,
    "adjacent_ai_hits": 1,
    "matched_concepts": [
      "adjacent_tech"
    ],
    "matched_tiers": [
      "adjacent_ai"
    ],
    "match_fields": [
      "raw_text"
    ],
    "in_ncsl": false,
    "source_bucket": "regex_flagged",
    "primary_url": "https://search-prod.lis.state.oh.us/solarapi/v1/general_assembly_134/bills/hb599/IN/00/hb599_00_IN?format=pdf",
    "latest_action_date": "2022-03-22",
    "latest_action_description": "Refer to Committee",
    "ncsl_status": ""
  },
  {
    "bill_id": "ocd-bill/055867ba-ca72-4df6-b640-1bc3f29e34e1",
    "state": "OH",
    "session": "136",
    "identifier": "HB 628",
    "title": "License artificial intelligence risk mitigation organizations",
    "updated": "",
    "core_ai_hits": 3,
    "adjacent_ai_hits": 1,
    "matched_concepts": [
      "artificial_intelligence",
      "adjacent_tech",
      "ai_system_composite",
      "ai_model_variant"
    ],
    "matched_tiers": [
      "core_ai",
      "adjacent_ai"
    ],
    "match_fields": [
      "raw_text",
      "title",
      "abstract"
    ],
    "in_ncsl": true,
    "source_bucket": "regex_flagged",
    "primary_url": "https://search-prod.lis.state.oh.us/api/v2/general_assembly_136/legislation/hb628/00_IN/pdf/",
    "latest_action_date": "2026-02-04T05:00:00+00:00",
    "latest_action_description": "Referred to committee",
    "ncsl_status": ""
  },
  {
    "bill_id": "ocd-bill/aa610bc3-6d93-4803-bd43-66ac5df64c05",
    "state": "OH",
    "session": "136",
    "identifier": "HB 646",
    "title": "Create the Data Center Study Commission",
    "updated": "",
    "core_ai_hits": 1,
    "adjacent_ai_hits": 0,
    "matched_concepts": [
      "artificial_intelligence"
    ],
    "matched_tiers": [
      "core_ai"
    ],
    "match_fields": [
      "raw_text"
    ],
    "in_ncsl": false,
    "source_bucket": "regex_flagged",
    "primary_url": "https://search-prod.lis.state.oh.us/api/v2/general_assembly_136/legislation/hb646/02_RH/pdf/",
    "latest_action_date": "2026-03-25T04:00:00+00:00",
    "latest_action_description": "Referred to committee",
    "ncsl_status": ""
  },
  {
    "bill_id": "ocd-bill/fead72db-f412-448b-9a8a-692a2cbe154a",
    "state": "OH",
    "session": "136",
    "identifier": "HB 650",
    "title": "Establish Frontier Technologies and Quantum Computing Commission",
    "updated": "",
    "core_ai_hits": 1,
    "adjacent_ai_hits": 0,
    "matched_concepts": [
      "artificial_intelligence"
    ],
    "matched_tiers": [
      "core_ai"
    ],
    "match_fields": [
      "raw_text"
    ],
    "in_ncsl": false,
    "source_bucket": "regex_flagged",
    "primary_url": "https://search-prod.lis.state.oh.us/api/v2/general_assembly_136/legislation/hb650/01_RH/pdf/",
    "latest_action_date": "2026-03-25T04:00:00+00:00",
    "latest_action_description": "Referred to committee",
    "ncsl_status": ""
  },
  {
    "bill_id": "ocd-bill/6ec92710-5af8-4d3f-b907-c88f37bdb717",
    "state": "OH",
    "session": "136",
    "identifier": "HB 663",
    "title": "Create the Artificial Intelligence Study Commission",
    "updated": "",
    "core_ai_hits": 1,
    "adjacent_ai_hits": 0,
    "matched_concepts": [
      "artificial_intelligence"
    ],
    "matched_tiers": [
      "core_ai"
    ],
    "match_fields": [
      "title",
      "raw_text",
      "abstract"
    ],
    "in_ncsl": true,
    "source_bucket": "regex_flagged",
    "primary_url": "https://search-prod.lis.state.oh.us/api/v2/general_assembly_136/legislation/hb663/00_IN/pdf/",
    "latest_action_date": "2026-02-04T05:00:00+00:00",
    "latest_action_description": "Referred to committee",
    "ncsl_status": ""
  },
  {
    "bill_id": "ocd-bill/2a2d1407-28fb-4b1d-9b13-56739343d64a",
    "state": "OH",
    "session": "136",
    "identifier": "HB 665",
    "title": "Regulate the use of pricing algorithms",
    "updated": "",
    "core_ai_hits": 1,
    "adjacent_ai_hits": 0,
    "matched_concepts": [
      "artificial_intelligence"
    ],
    "matched_tiers": [
      "core_ai"
    ],
    "match_fields": [
      "raw_text"
    ],
    "in_ncsl": true,
    "source_bucket": "regex_flagged",
    "primary_url": "https://search-prod.lis.state.oh.us/api/v2/general_assembly_136/legislation/hb665/00_IN/pdf/",
    "latest_action_date": "2026-02-04T05:00:00+00:00",
    "latest_action_description": "Referred to committee",
    "ncsl_status": ""
  },
  {
    "bill_id": "ocd-bill/0c06015f-6c27-4204-9944-c3530d4b6e6f",
    "state": "OH",
    "session": "136",
    "identifier": "HB 775",
    "title": "Regards state agencies' authority to adopt administrative rules",
    "updated": "",
    "core_ai_hits": 0,
    "adjacent_ai_hits": 1,
    "matched_concepts": [
      "adjacent_tech"
    ],
    "matched_tiers": [
      "adjacent_ai"
    ],
    "match_fields": [
      "raw_text"
    ],
    "in_ncsl": false,
    "source_bucket": "regex_flagged",
    "primary_url": "https://search-prod.lis.state.oh.us/api/v2/general_assembly_136/legislation/hb775/00_IN/pdf/",
    "latest_action_date": "2026-03-25T04:00:00+00:00",
    "latest_action_description": "Referred to committee",
    "ncsl_status": ""
  },
  {
    "bill_id": "ocd-bill/bee1ae42-bc3f-4ac6-9135-559d7d7500a6",
    "state": "OH",
    "session": "136",
    "identifier": "HB 786",
    "title": "Prohibit artificial depiction of a minor for obscene purposes",
    "updated": "",
    "core_ai_hits": 1,
    "adjacent_ai_hits": 0,
    "matched_concepts": [
      "artificial_intelligence"
    ],
    "matched_tiers": [
      "core_ai"
    ],
    "match_fields": [
      "raw_text"
    ],
    "in_ncsl": false,
    "source_bucket": "regex_flagged",
    "primary_url": "https://search-prod.lis.state.oh.us/api/v2/general_assembly_136/legislation/hb786/00_IN/pdf/",
    "latest_action_date": "2026-03-25T04:00:00+00:00",
    "latest_action_description": "Referred to committee",
    "ncsl_status": ""
  },
  {
    "bill_id": "ocd-bill/4e02024d-881d-4a05-9191-b218c16ecff4",
    "state": "OH",
    "session": "136",
    "identifier": "HB 96",
    "title": "Make state operating appropriations for FY 2026-27",
    "updated": "",
    "core_ai_hits": 1,
    "adjacent_ai_hits": 1,
    "matched_concepts": [
      "adjacent_tech",
      "artificial_intelligence"
    ],
    "matched_tiers": [
      "adjacent_ai",
      "core_ai"
    ],
    "match_fields": [
      "raw_text"
    ],
    "in_ncsl": true,
    "source_bucket": "regex_flagged",
    "primary_url": "https://search-prod.lis.state.oh.us/api/v2/general_assembly_136/legislation/hb96/04_RS/pdf/",
    "latest_action_date": "2025-10-01T04:00:00+00:00",
    "latest_action_description": "Item passed notwithstanding objections of the Governor",
    "ncsl_status": ""
  },
  {
    "bill_id": "ocd-bill/75861f14-c1fc-4044-a941-21efe636514e",
    "state": "OH",
    "session": "136",
    "identifier": "HCR 12",
    "title": "Recognize the importance of perinatal mental health",
    "updated": "",
    "core_ai_hits": 0,
    "adjacent_ai_hits": 1,
    "matched_concepts": [
      "adjacent_tech"
    ],
    "matched_tiers": [
      "adjacent_ai"
    ],
    "match_fields": [
      "raw_text"
    ],
    "in_ncsl": false,
    "source_bucket": "regex_flagged",
    "primary_url": "https://search-prod.lis.state.oh.us/api/v2/general_assembly_136/legislation/hcr12/00_IN/pdf/",
    "latest_action_date": "2025-04-30T04:00:00+00:00",
    "latest_action_description": "Introduced and Referred to Committee",
    "ncsl_status": ""
  },
  {
    "bill_id": "ocd-bill/7bdcc01b-2623-421d-9f05-97fa7bff78f9",
    "state": "OH",
    "session": "135",
    "identifier": "HCR 16",
    "title": "Recognizing the importance of perinatal mental health",
    "updated": "",
    "core_ai_hits": 0,
    "adjacent_ai_hits": 1,
    "matched_concepts": [
      "adjacent_tech"
    ],
    "matched_tiers": [
      "adjacent_ai"
    ],
    "match_fields": [
      "raw_text"
    ],
    "in_ncsl": true,
    "source_bucket": "regex_flagged",
    "primary_url": "https://search-prod.lis.state.oh.us/solarapi/v1/general_assembly_135/resolutions/hcr16/RH/02/hcr16_02_RH?format=pdf",
    "latest_action_date": "2024-12-17",
    "latest_action_description": "Offered",
    "ncsl_status": "Pending"
  },
  {
    "bill_id": "ocd-bill/70876269-5f18-4ab6-b221-8fb11346eab3",
    "state": "OH",
    "session": "136",
    "identifier": "HCR 31",
    "title": "Urge Congress to reject any moratorium on state AI laws",
    "updated": "",
    "core_ai_hits": 1,
    "adjacent_ai_hits": 0,
    "matched_concepts": [
      "artificial_intelligence"
    ],
    "matched_tiers": [
      "core_ai"
    ],
    "match_fields": [
      "abstract",
      "raw_text"
    ],
    "in_ncsl": true,
    "source_bucket": "regex_flagged",
    "primary_url": "https://search-prod.lis.state.oh.us/api/v2/general_assembly_136/legislation/hcr31/00_IN/pdf/",
    "latest_action_date": "2026-02-04T05:00:00+00:00",
    "latest_action_description": "Introduced and Referred to Committee",
    "ncsl_status": ""
  },
  {
    "bill_id": "ocd-bill/174e4ace-f072-4bb1-9a14-dda0d12b8b1e",
    "state": "OH",
    "session": "136",
    "identifier": "HR 11",
    "title": "Urge Ohio expansion of manufacturing of domestic drones",
    "updated": "",
    "core_ai_hits": 1,
    "adjacent_ai_hits": 0,
    "matched_concepts": [
      "artificial_intelligence"
    ],
    "matched_tiers": [
      "core_ai"
    ],
    "match_fields": [
      "raw_text"
    ],
    "in_ncsl": true,
    "source_bucket": "regex_flagged",
    "primary_url": "https://search-prod.lis.state.oh.us/api/v2/general_assembly_136/legislation/hr11/00_IN/pdf/",
    "latest_action_date": "2025-01-28T05:00:00+00:00",
    "latest_action_description": "Introduced and Referred to Committee",
    "ncsl_status": "Pending"
  },
  {
    "bill_id": "ocd-bill/04e56ffa-f4a8-48fe-83e5-a3de125e7758",
    "state": "OH",
    "session": "135",
    "identifier": "SB 1",
    "title": "Revise Education Law and Department duties; rename the Department",
    "updated": "",
    "core_ai_hits": 0,
    "adjacent_ai_hits": 1,
    "matched_concepts": [
      "adjacent_tech"
    ],
    "matched_tiers": [
      "adjacent_ai"
    ],
    "match_fields": [
      "raw_text"
    ],
    "in_ncsl": false,
    "source_bucket": "regex_flagged",
    "primary_url": "https://search-prod.lis.state.oh.us/solarapi/v1/general_assembly_135/bills/sb1/RS/01/sb1_01_RS?format=pdf",
    "latest_action_date": "2023-03-14",
    "latest_action_description": "Refer to Committee",
    "ncsl_status": ""
  },
  {
    "bill_id": "ocd-bill/51b93c91-e5be-4335-9683-e3808259b010",
    "state": "OH",
    "session": "135",
    "identifier": "SB 156",
    "title": "Regards designation of wild, scenic, and recreational rivers",
    "updated": "",
    "core_ai_hits": 0,
    "adjacent_ai_hits": 1,
    "matched_concepts": [
      "adjacent_tech"
    ],
    "matched_tiers": [
      "adjacent_ai"
    ],
    "match_fields": [
      "raw_text"
    ],
    "in_ncsl": false,
    "source_bucket": "regex_flagged",
    "primary_url": "https://search-prod.lis.state.oh.us/solarapi/v1/general_assembly_135/bills/sb156/RS/01/sb156_01_RS?format=pdf",
    "latest_action_date": "2024-10-24T04:00:00+00:00",
    "latest_action_description": "Effective 10/24/24",
    "ncsl_status": ""
  },
  {
    "bill_id": "ocd-bill/8fe9ce82-9df8-4264-bf29-d63a27882beb",
    "state": "OH",
    "session": "136",
    "identifier": "SB 163",
    "title": "Regards AI images, simulated child porn, replica identity fraud",
    "updated": "",
    "core_ai_hits": 3,
    "adjacent_ai_hits": 0,
    "matched_concepts": [
      "ai_system_composite",
      "artificial_intelligence",
      "ai_system"
    ],
    "matched_tiers": [
      "core_ai"
    ],
    "match_fields": [
      "raw_text"
    ],
    "in_ncsl": true,
    "source_bucket": "regex_flagged",
    "primary_url": "https://search-prod.lis.state.oh.us/api/v2/general_assembly_136/legislation/sb163/00_IN/pdf/",
    "latest_action_date": "2025-04-02T04:00:00+00:00",
    "latest_action_description": "Referred to committee",
    "ncsl_status": ""
  },
  {
    "bill_id": "ocd-bill/43851aef-176d-4db0-910f-29c855878c9b",
    "state": "OH",
    "session": "136",
    "identifier": "SB 164",
    "title": "Regulate the use of artificial intelligence by health insurers",
    "updated": "",
    "core_ai_hits": 1,
    "adjacent_ai_hits": 0,
    "matched_concepts": [
      "artificial_intelligence"
    ],
    "matched_tiers": [
      "core_ai"
    ],
    "match_fields": [
      "abstract",
      "raw_text",
      "title"
    ],
    "in_ncsl": true,
    "source_bucket": "regex_flagged",
    "primary_url": "https://search-prod.lis.state.oh.us/api/v2/general_assembly_136/legislation/sb164/00_IN/pdf/",
    "latest_action_date": "2025-04-02T04:00:00+00:00",
    "latest_action_description": "Referred to committee",
    "ncsl_status": ""
  },
  {
    "bill_id": "ocd-bill/a0066c0b-15ce-4ef9-b011-bcaf642f0e7b",
    "state": "OH",
    "session": "134",
    "identifier": "SB 178",
    "title": "Reform function, responsibilities of state education offices",
    "updated": "",
    "core_ai_hits": 0,
    "adjacent_ai_hits": 1,
    "matched_concepts": [
      "adjacent_tech"
    ],
    "matched_tiers": [
      "adjacent_ai"
    ],
    "match_fields": [
      "raw_text"
    ],
    "in_ncsl": false,
    "source_bucket": "regex_flagged",
    "primary_url": "https://search-prod.lis.state.oh.us/solarapi/v1/general_assembly_134/bills/sb178/RS/01/sb178_01_RS?format=pdf",
    "latest_action_date": "2022-12-13",
    "latest_action_description": "Refer to Committee",
    "ncsl_status": ""
  },
  {
    "bill_id": "ocd-bill/37720074-0a23-4661-8bcd-495cfd53318b",
    "state": "OH",
    "session": "135",
    "identifier": "SB 217",
    "title": "Regards AI-generated products, simulated porn, identity fraud",
    "updated": "",
    "core_ai_hits": 3,
    "adjacent_ai_hits": 0,
    "matched_concepts": [
      "ai_system_composite",
      "ai_system",
      "artificial_intelligence"
    ],
    "matched_tiers": [
      "core_ai"
    ],
    "match_fields": [
      "raw_text"
    ],
    "in_ncsl": true,
    "source_bucket": "regex_flagged",
    "primary_url": "https://search-prod.lis.state.oh.us/solarapi/v1/general_assembly_135/bills/sb217/IN/00/sb217_00_IN?format=pdf",
    "latest_action_date": "2024-02-28",
    "latest_action_description": "Refer to Committee",
    "ncsl_status": ""
  },
  {
    "bill_id": "ocd-bill/716cca8e-17f4-4612-ab5f-9eea6a6d5a4a",
    "state": "OH",
    "session": "135",
    "identifier": "SB 274",
    "title": "Revise the Election Law",
    "updated": "",
    "core_ai_hits": 0,
    "adjacent_ai_hits": 1,
    "matched_concepts": [
      "adjacent_tech"
    ],
    "matched_tiers": [
      "adjacent_ai"
    ],
    "match_fields": [
      "raw_text"
    ],
    "in_ncsl": false,
    "source_bucket": "regex_flagged",
    "primary_url": "https://search-prod.lis.state.oh.us/solarapi/v1/general_assembly_135/bills/sb274/IN/00/sb274_00_IN?format=pdf",
    "latest_action_date": "2024-06-11",
    "latest_action_description": "Refer to Committee",
    "ncsl_status": ""
  },
  {
    "bill_id": "ocd-bill/4b133382-61d6-4a2b-951d-c1c5a3cfb41a",
    "state": "OH",
    "session": "136",
    "identifier": "SB 326",
    "title": "Require students complete a high school computer science course",
    "updated": "",
    "core_ai_hits": 1,
    "adjacent_ai_hits": 0,
    "matched_concepts": [
      "artificial_intelligence"
    ],
    "matched_tiers": [
      "core_ai"
    ],
    "match_fields": [
      "raw_text"
    ],
    "in_ncsl": true,
    "source_bucket": "regex_flagged",
    "primary_url": "https://search-prod.lis.state.oh.us/api/v2/general_assembly_136/legislation/sb326/00_IN/pdf/",
    "latest_action_date": "2025-11-18T05:00:00+00:00",
    "latest_action_description": "Referred to committee",
    "ncsl_status": ""
  },
  {
    "bill_id": "ocd-bill/ea92999a-6281-4ada-a2c4-781ceb8d6583",
    "state": "OH",
    "session": "135",
    "identifier": "SB 328",
    "title": "Regulate use of pricing algorithms",
    "updated": "",
    "core_ai_hits": 1,
    "adjacent_ai_hits": 0,
    "matched_concepts": [
      "artificial_intelligence"
    ],
    "matched_tiers": [
      "core_ai"
    ],
    "match_fields": [
      "raw_text"
    ],
    "in_ncsl": false,
    "source_bucket": "regex_flagged",
    "primary_url": "https://search-prod.lis.state.oh.us/solarapi/v1/general_assembly_135/bills/sb328/IN/00/sb328_00_IN?format=pdf",
    "latest_action_date": "2024-11-13",
    "latest_action_description": "Refer to Committee",
    "ncsl_status": ""
  },
  {
    "bill_id": "ocd-bill/22552b9d-7592-4824-b4cb-7c2a2021b290",
    "state": "OH",
    "session": "136",
    "identifier": "SB 393",
    "title": "Regards sexually oriented offenses involving juveniles, animals",
    "updated": "",
    "core_ai_hits": 1,
    "adjacent_ai_hits": 0,
    "matched_concepts": [
      "artificial_intelligence"
    ],
    "matched_tiers": [
      "core_ai"
    ],
    "match_fields": [
      "raw_text"
    ],
    "in_ncsl": true,
    "source_bucket": "regex_flagged",
    "primary_url": "https://search-prod.lis.state.oh.us/api/v2/general_assembly_136/legislation/sb393/00_IN/pdf/",
    "latest_action_date": "2026-03-24T04:00:00+00:00",
    "latest_action_description": "Referred to committee",
    "ncsl_status": ""
  },
  {
    "bill_id": "ocd-bill/64d8ac1d-61b4-46cc-b84d-ff16db83cf05",
    "state": "OH",
    "session": "136",
    "identifier": "SB 79",
    "title": "Regulate the use of pricing algorithms",
    "updated": "",
    "core_ai_hits": 1,
    "adjacent_ai_hits": 0,
    "matched_concepts": [
      "artificial_intelligence"
    ],
    "matched_tiers": [
      "core_ai"
    ],
    "match_fields": [
      "raw_text"
    ],
    "in_ncsl": true,
    "source_bucket": "regex_flagged",
    "primary_url": "https://search-prod.lis.state.oh.us/api/v2/general_assembly_136/legislation/sb79/00_IN/pdf/",
    "latest_action_date": "2025-02-12T05:00:00+00:00",
    "latest_action_description": "Referred to committee",
    "ncsl_status": ""
  },
  {
    "bill_id": "ocd-bill/e4f4e322-3037-42ed-8f27-2c06107112e9",
    "state": "OH",
    "session": "136",
    "identifier": "SCR 14",
    "title": "Urge Congress to reject moratorium on state regulation of AI",
    "updated": "",
    "core_ai_hits": 1,
    "adjacent_ai_hits": 0,
    "matched_concepts": [
      "artificial_intelligence"
    ],
    "matched_tiers": [
      "core_ai"
    ],
    "match_fields": [
      "abstract",
      "raw_text"
    ],
    "in_ncsl": true,
    "source_bucket": "regex_flagged",
    "primary_url": "https://search-prod.lis.state.oh.us/api/v2/general_assembly_136/legislation/scr14/00_IN/pdf/",
    "latest_action_date": "2026-02-11T05:00:00+00:00",
    "latest_action_description": "Referred to committee",
    "ncsl_status": ""
  },
  {
    "bill_id": "ocd-bill/98571fd5-e587-4028-a55b-fc7273a3de52",
    "state": "OH",
    "session": "136",
    "identifier": "SR 304",
    "title": "Honor Pope Leo XIV; highlight his life and accomplishments",
    "updated": "",
    "core_ai_hits": 1,
    "adjacent_ai_hits": 0,
    "matched_concepts": [
      "artificial_intelligence"
    ],
    "matched_tiers": [
      "core_ai"
    ],
    "match_fields": [
      "raw_text"
    ],
    "in_ncsl": false,
    "source_bucket": "regex_flagged",
    "primary_url": "https://search-prod.lis.state.oh.us/api/v2/general_assembly_136/legislation/sr304/00_IN/pdf/",
    "latest_action_date": "2026-03-26T04:00:00+00:00",
    "latest_action_description": "Offered",
    "ncsl_status": ""
  }
]